{"_id":"07394adc-2610-30dc-82a7-3995ddd69b9a","authorName":"Stephen Cleary","authorEmailEncrypted":"","authorEmailMD5":"3db7b6e14d9da42751e4bab03bc4d034","authorUri":"https://stephencleary.com/","authorUserId":"","authorFallbackAvatar":"","message":"Yes. We also use (abuse?) IDisposable for unsubscribing to everything at the end of life (this was a more controversial decision).  \r\n\r\nInternally, the Path is split by the member access operator and a SimplePropertyPath.SubscriptionStep is built for each member access (so \"a.b.c\" has three subscription steps). The (private) SimplePropertyPath.Dismantle method will unsubscribe all subscription steps from a certain index forward, and SimplePropertyPath.Construct will re-evaluate and subscribe each subscription step from a certain index forward.  \r\n\r\nThe source is available for download, though the first official release is still several weeks away. SimplePropertyPath is one of the more mature classes, and could be considered in a RC stage.","postId":"2009_07_this-post-illustrates-one-of-several-dc1da2ad-2b5e-3428-8faf-4e7866cf18b1","replyTo":"","date":"2009-08-02T18:26:32Z","timestamp":1249237592}