{"_id":"f8c60e94-8841-30b6-8adc-e26e75ee59da","authorName":"Gerard Hermans","authorEmailEncrypted":"","authorEmailMD5":"","authorUri":"http://www.blogger.com/profile/10454587573921552244","authorUserId":"","authorFallbackAvatar":"","message":"I used the class NotifyTaskCompletion from the AsyncEx library in my project and it works nicely.  \r\nHowever I ran into the issue that I had to notify an extra PropertyChanged after the Task completed and the Result was set in MyProperty.  \r\nI.e. another property of the viewmodel (not MyProperty).  \r\nI could only get it to work to pass on the delegate of my raisePropertyChanged and my property-name to class NotifyTaskCompletion.","postId":"2013_01_async-oop-3-properties-a63cc351-e3f4-3a7c-be7a-928114355720","replyTo":"","date":"2013-11-21T16:52:53Z","timestamp":1385052773}