{"_id":"ff734681-4664-34c0-9ae4-8cac32d96940","authorName":"Stephen Cleary","authorEmailEncrypted":"","authorEmailMD5":"3db7b6e14d9da42751e4bab03bc4d034","authorUri":"https://stephencleary.com/","authorUserId":"","authorFallbackAvatar":"","message":"AsyncContext only executes one task at a time. So if you block a task (e.g., ReadKey), then the tasks queued by StartNew cannot execute until that task completes.","postId":"2012_02_async-console-programs-2120b75e-4001-37ec-a5ad-04ca51ccb801","replyTo":"","date":"2014-02-22T22:07:56Z","timestamp":1393106876}