{"_id":"89e80799-66a9-3b33-b87d-e4065b57b56f","authorName":"Stephen Cleary","authorEmailEncrypted":"","authorEmailMD5":"3db7b6e14d9da42751e4bab03bc4d034","authorUri":"https://stephencleary.com/","authorUserId":"","authorFallbackAvatar":"","message":"Actually - and this may sound weird - one of the most straightforward ways I debug multithreaded code is to just read it. I don't have a lot of experience using the VS multithreading debugging tools.","postId":"2015_05_thatconference-1a3e1f0e-197f-34d4-857c-efaba4a4a73c","replyTo":"f95bb119-8f39-3544-9674-a59ad3aa2764","date":"2015-05-29T11:43:14Z","timestamp":1432899794}