{"_id":"50f7875b-ef7e-3516-b4a5-2ba91aaf283a","authorName":"Stephen Cleary","authorEmailEncrypted":"","authorEmailMD5":"3db7b6e14d9da42751e4bab03bc4d034","authorUri":"https://stephencleary.com/","authorUserId":"","authorFallbackAvatar":"","message":"Hi, Piet,\r\n\r\nThere isn't enough information in the question to be able to answer it. I recommend that you reduce the case to the smallest reproducible example and then post it on Stack Overflow.","postId":"2012_07_dont-block-on-async-code-abe2d9c7-c3e9-3ed8-827c-021686fa2310","replyTo":"7407f97b-dbe4-34cd-b893-12472c158ded","date":"2015-11-11T13:17:07Z","timestamp":1447247827}